CHANGELOG.txt
LICENSE.txt
MANIFEST.in
README.txt
main.py
setup.py
cex_webuy_api/__init__.py
cex_webuy_api.egg-info/PKG-INFO
cex_webuy_api.egg-info/SOURCES.txt
cex_webuy_api.egg-info/dependency_links.txt
cex_webuy_api.egg-info/requires.txt
cex_webuy_api.egg-info/top_level.txt