Metadata-Version: 1.1
Name: cex-webuy-api
Version: 0.0.2
Summary: CeX WeBuy API Wrapper
Home-page: http://pythoncasovi.com
Author: Darko Dekan
Author-email: darko.dekan@protonmail.com
License: The Unlicense (Unlicense)
Keywords: cex,webuy,api,product,stock
Platform: UNKNOWN
Classifier: Development Status :: 5 - Production/Stable
Classifier: Intended Audience :: Developers
Classifier: Operating System :: POSIX :: Linux
Classifier: License :: OSI Approved :: The Unlicense (Unlicense)
Classifier: Programming Language :: Python :: 3.9
